LICENSE
README.md
setup.py
process_street_tap_postgres.egg-info/PKG-INFO
process_street_tap_postgres.egg-info/SOURCES.txt
process_street_tap_postgres.egg-info/dependency_links.txt
process_street_tap_postgres.egg-info/entry_points.txt
process_street_tap_postgres.egg-info/requires.txt
process_street_tap_postgres.egg-info/top_level.txt
tap_postgres/__init__.py
tap_postgres/db.py
tap_postgres/discovery_utils.py
tap_postgres/stream_utils.py
tap_postgres/sync_strategies/__init__.py
tap_postgres/sync_strategies/common.py
tap_postgres/sync_strategies/full_table.py
tap_postgres/sync_strategies/incremental.py
tap_postgres/sync_strategies/logical_replication.py