Metadata-Version: 2.1
Name: process-street-tap-postgres
Version: 2.1.0
Summary: Singer.io tap for extracting data from PostgresSQL - PipelineWise compatible
Home-page: https://github.com/process-street/process-street-tap-postgres
Author: Process Street
License: UNKNOWN
Platform: UNKNOWN
Classifier: License :: OSI Approved :: GNU Affero General Public License v3
Classifier: Programming Language :: Python :: 3 :: Only
Requires-Python: >=3.7,<3.10
Provides-Extra: test
License-File: LICENSE
